tpMayaLib/__init__.py
tpMayaLib/core/__init__.py
tpMayaLib/core/api.py
tpMayaLib/core/attribute.py
tpMayaLib/core/blendshape.py
tpMayaLib/core/callback.py
tpMayaLib/core/camera.py
tpMayaLib/core/color.py
tpMayaLib/core/common.py
tpMayaLib/core/component.py
tpMayaLib/core/constants.py
tpMayaLib/core/constraint.py
tpMayaLib/core/contexts.py
tpMayaLib/core/control.py
tpMayaLib/core/curve.py
tpMayaLib/core/dcc.py
tpMayaLib/core/decorators.py
tpMayaLib/core/deformer.py
tpMayaLib/core/directory.py
tpMayaLib/core/distance.py
tpMayaLib/core/exceptions.py
tpMayaLib/core/geometry.py
tpMayaLib/core/gui.py
tpMayaLib/core/helpers.py
tpMayaLib/core/ik.py
tpMayaLib/core/joint.py
tpMayaLib/core/layer.py
tpMayaLib/core/mash.py
tpMayaLib/core/mathutils.py
tpMayaLib/core/matrix.py
tpMayaLib/core/mayapymanager.py
tpMayaLib/core/menu.py
tpMayaLib/core/mesh.py
tpMayaLib/core/modelpanel.py
tpMayaLib/core/name.py
tpMayaLib/core/namespace.py
tpMayaLib/core/node.py
tpMayaLib/core/playblast.py
tpMayaLib/core/qtutils.py
tpMayaLib/core/rig.py
tpMayaLib/core/scene.py
tpMayaLib/core/shader.py
tpMayaLib/core/shape.py
tpMayaLib/core/shelf.py
tpMayaLib/core/skin.py
tpMayaLib/core/space.py
tpMayaLib/core/symmetry.py
tpMayaLib/core/thumbnail.py
tpMayaLib/core/time.py
tpMayaLib/core/transform.py
tpMayaLib/core/viewport.py
tpMayaLib/core/window.py
tpMayaLib/data/__init__.py
tpMayaLib/data/base.py
tpMayaLib/data/curve.py
tpMayaLib/data/deformer.py
tpMayaLib/data/mesh.py
tpMayaLib/data/skin.py
tpMayaLib/managers/__init__.py
tpMayaLib/managers/metadatamanager.py
tpMayaLib/meta/__init__.py
tpMayaLib/meta/metaattribute.py
tpMayaLib/meta/metanode.py
tpMayaLib/meta/metaobject.py
tpMayaLib/meta/metautils.py
tpmayalib-0.0.2.dist-info/LICENSE
tpmayalib-0.0.2.dist-info/METADATA
tpmayalib-0.0.2.dist-info/WHEEL
tpmayalib-0.0.2.dist-info/top_level.txt
tpmayalib-0.0.2.dist-info/RECORD
