Metadata-Version: 2.1
Name: tpmayalib
Version: 0.0.2
Summary: Maya implementation for tpDccLib and tpQtLib. Utils functions to work with Maya Python APIs.
Home-page: https://github.com/tpoveda/tpMayaLib
Author: Tomas Poveda
Author-email: tpovedatd@gmail.com
License: MIT
Platform: UNKNOWN
Provides-Extra: dev
Requires-Dist: wheel ; extra == 'dev'
Provides-Extra: test
Requires-Dist: pytest ; extra == 'test'
